dolores/__init__.py
dolores/dolores.py
dolores/version.py
tests/__init__.py
tests/conftest.py
tests/test_dolores.py
dolores-1.0.3.dist-info/LICENSE
dolores-1.0.3.dist-info/METADATA
dolores-1.0.3.dist-info/WHEEL
dolores-1.0.3.dist-info/top_level.txt
dolores-1.0.3.dist-info/RECORD
