Metadata-Version: 2.1
Name: dolores
Version: 1.0.3
Summary: Dolores is a Python library for developers using GPT-3.
Home-page: https://github.com/dne-digital/dolores
Author: Phil Mohun, Malcolm Navarro, DNE LLC
Author-email: dolores@philmohun.com
License: UNKNOWN
Download-URL: https://pypi.org/project/dolores/
Platform: UNKNOWN
Classifier: Programming Language :: Python :: 3
Classifier: License :: OSI Approved :: BSD License
Classifier: Operating System :: OS Independent
Requires-Python: >=3.6
